odoo/addons/stock_move_pivot_total_price/README.rst
odoo/addons/stock_move_pivot_total_price/__init__.py
odoo/addons/stock_move_pivot_total_price/__manifest__.py
odoo/addons/stock_move_pivot_total_price/hooks.py
odoo/addons/stock_move_pivot_total_price/i18n/ca.po
odoo/addons/stock_move_pivot_total_price/i18n/es.po
odoo/addons/stock_move_pivot_total_price/i18n/it.po
odoo/addons/stock_move_pivot_total_price/i18n/stock_move_pivot_total_price.pot
odoo/addons/stock_move_pivot_total_price/models/__init__.py
odoo/addons/stock_move_pivot_total_price/models/stock_move.py
odoo/addons/stock_move_pivot_total_price/readme/CONTRIBUTORS.md
odoo/addons/stock_move_pivot_total_price/readme/DESCRIPTION.md
odoo/addons/stock_move_pivot_total_price/readme/USAGE.md
odoo/addons/stock_move_pivot_total_price/static/description/icon.png
odoo/addons/stock_move_pivot_total_price/static/description/index.html
odoo/addons/stock_move_pivot_total_price/tests/__init__.py
odoo/addons/stock_move_pivot_total_price/tests/test_product_total_price.py
odoo/addons/stock_move_pivot_total_price/views/stock_move.xml
odoo_addon_stock_move_pivot_total_price-17.0.1.0.0.4.dist-info/METADATA
odoo_addon_stock_move_pivot_total_price-17.0.1.0.0.4.dist-info/WHEEL
odoo_addon_stock_move_pivot_total_price-17.0.1.0.0.4.dist-info/top_level.txt
odoo_addon_stock_move_pivot_total_price-17.0.1.0.0.4.dist-info/RECORD
