Metadata-Version: 2.1
Name: odoo-addon-stock_move_pivot_total_price
Version: 17.0.1.0.0.4
Requires-Python: >=3.10
Requires-Dist: odoo>=17.0a,<17.1dev
Summary: Adds a total price UOM to the stock move pivot view
Home-page: https://github.com/OCA/stock-logistics-reporting
License: AGPL-3
Author: Odoo Community Association (OCA), APSL-Nagarro
Author-email: support@odoo-community.org
Classifier: Programming Language :: Python
Classifier: Framework :: Odoo
Classifier: Framework :: Odoo :: 17.0
Classifier: License :: OSI Approved :: GNU Affero General Public License v3
